{
  "pages": [
    {
      "title": "首页",
      "path": "/home",
      "text": ""
    },
    {
      "title": "日志",
      "path": "/article",
      "text": ""
    },
    {
      "title": "关于",
      "path": "/about",
      "text": ""
    },
    {
      "title": "留言",
      "path": "/message",
      "text": ""
    }
  ],
  "posts": [
    {
      "id": 2,
      "categories": [],
      "date": "2022-03-21",
      "title": "在人间",
      "text": "2022年3月21日14时38分许 ，一架中国东方航空集团有限公司波音737-800客机在广西壮族自治区梧州市藤县埌南镇莫埌村神塘表附近山林坠毁，并引发山火。  闭上眼睛 思绪飘向空难雨夜的山谷，彷佛听到一声声呼救，一声声 回家。",
      "link": "http://rluot02vo.hd-bkt.clouddn.com/images/IMG_20220909_111102.jpg",
      "content": "乌云从天边蔓延 蜷着咸咸的雨 在山谷的夜晚游离曼逸 愿它能安慰土地和土地里。 春天的造物者在梦中呓语 “回家去 要回家去” 萤火虫扯掉外衣 在春天的拥抱中喑哑 “想念你 好想念你” 黑色的大地在啜泣 灯火里一双流泪的眼睛  美丽的湖塞尼 寂静如同顽疾滋长 在人世间",
      "tags": [
        {
          "name": "空难",
          "slug": "雨夜",
          "permalink": ""
        }
      ]
    },
    {
      "id": 3,
      "categories": [],
      "date": "2022-10-03",
      "title": "如果可以",
      "text": "",
      "link": "http://rluot02vo.hd-bkt.clouddn.com/images/IMG_20210102_160345.jpg",
      "content": "如果可以的话 花瓣也要铺满贫瘠的沙漠 云朵也要拥抱一整个蓝天 鸟儿从远方传来消息 于是我不愿意在混浊 我张开双臂拥抱所有 热情地 疯狂地 心里不停歇地呐喊着 用我最真诚的声音对你说 所有关于人类对梦的阐述 慢慢地绕成一条条彩色的带子 它告诉我的我必须告诉每一个人 我一直在这里停留  风悄悄地也在这里驻足 顺着它的方向 我想你",
      "tags": [
        {
          "name": "自由",
          "slug": "",
          "permalink": ""
        }
      ]
    },
    {
      "id": 4,
      "categories": [],
      "date": "2022-09-30",
      "title": "今夜",
      "text": "",
      "link": "http://rluot02vo.hd-bkt.clouddn.com/images/IMG_20210619_192136.jpg",
      "content": "如果我停止爱你 肆意飞翔的鸟儿 请把我啄醒 疲惫不堪地颤抖着 急切地寻你  假如我放浪形骸 要拖着月亮穿越无边的天际 可今夜我不会停止爱你 爱你是我永恒生命的证明 月亮盈盈 映在你脸庞 不要思念 在今夜 亲爱的湖塞尼 如果你要哭泣 不要在这个寒冷的夜晚",
      "tags": [
        {
          "name": "爱情 向往",
          "slug": "怪谈",
          "permalink": ""
        }
      ]
    },
    {
      "id": 5,
      "categories": [],
      "date": "2022-02-06",
      "title": "送别",
      "text": "",
      "link": "http://rluot02vo.hd-bkt.clouddn.com/images/IMG_20220927_113717.jpg",
      "content": "乌云 踩着缆线在窗上跳舞 北方的雪 是不是你在写下我的名字  临入夜 没有再看到你的痕迹 北方的雪呵 天上的是月亮还是太阳？  可要唤醒我的名字 派雪花来追刺骨的风啊 要再唤声我的名字 向呼喊的方向再近一步啊  北方的雪啊 见不到你却说不想你 ",
      "tags": [
        {
          "name": "远行 送别",
          "slug": "远行",
          "permalink": ""
        }
      ]
    },
    {
      "id": 1,
      "categories": [],
      "date": "2021-07-12",
      "title": "盼来",
      "text": "",
      "link": "http://rluot02vo.hd-bkt.clouddn.com/images/IMG_20210619_192136.jpg",
      "content": "灯尾随 我游荡的街口 轻轻啊 别打扰细雨风 掠过的虫草  天灰灰 知了叫了又叫 掰掰手指头 汲汲啊 又走过了道  船飘在 戈壁里彩绘的湖上 一次两次 推着星星闪耀 慢慢啊",
      "tags": [
        {
          "name": "时光已逝 青春",
          "slug": "",
          "permalink": ""
        }
      ]
    },
    {
      "id": 6,
      "categories": [],
      "date": "2020-12-10",
      "title": "小巷",
      "text": "",
      "link": "http://rluot02vo.hd-bkt.clouddn.com/images/mmexport1599122115860.jpg",
      "content": "这清净的街道我在这里 透过眼睛送给记忆中的你 包括两旁翠绿的树  给你我的专注里 复杂又空洞的神情 给你我的悲喜里 能发现每处夹杂着稀疏的美丽  给你我梦里 斜阳下印着花瓣的小溪 盛放有晚霞的秘密 上面有纹路 是我探索的轨迹 别去关心是这里 还是哪里  再把这一节书签抽出来给你 是关于一个人的记忆 它描述一段惊人的生命力  风帮树叶做回自己 星星带着我的期许 小巷里没有人过 小巷默许了这一切",
      "tags": [
        {
          "name": "枫叶 晚秋",
          "slug": "小巷",
          "permalink": ""
        }
      ]
    },
    {
      "id": 7,
      "categories": [],
      "date": "2020-11-18",
      "title": "美丽面具",
      "text": "",
      "link": "http://rluot02vo.hd-bkt.clouddn.com/images/IMG_20201018_125448.jpg",
      "content": "第一次睁开眼 刚到夜里 马上明天的我就要告别今天的我的夜里 闭上眼美丽都围绕着你 美丽也羡慕你  又一次睁开眼 你仍然华丽的站在光鲜里 而美丽蜷缩着身体 不再粉饰你 闭上眼美丽也变得不美丽 美丽比不上你  最后一次睁开眼 夜要离去 今天的我同样称赞你美丽 早上的雾气 雾气一直不散去 闭眼上美丽躲在我眼里 告诉我你的秘密",
      "tags": [
        {
          "name": "午夜",
          "slug": "",
          "permalink": ""
        }
      ]
    },
    {
      "id": 8,
      "categories": [],
      "date": "2020-07-24",
      "title": "雷雨",
      "text": "",
      "link": "http://rluot02vo.hd-bkt.clouddn.com/images/IMG_20200403_181019.jpg",
      "content": "无意间想到你 都归功于这场雨 和几声雷鸣 忘了撑手里破旧的伞 你贴进我 在雾蒙蒙里  慢慢又细腻 街道等不及的车辆鸣笛 现在的我浸在雨里 两个我在想你。",
      "tags": [
        {
          "name": "雨伞 雷雨",
          "slug": "初夏",
          "permalink": ""
        }
      ]
    }
  ]
}
